mjxml/__init__.py
mjxml/commons.py
mjxml/model.py
mjxml/rotations.py
mjxml/typeutils.py
mjxml/actuator/__init__.py
mjxml/actuator/general.py
mjxml/asset/__init__.py
mjxml/asset/asset.py
mjxml/asset/hfield.py
mjxml/asset/material.py
mjxml/asset/mesh.py
mjxml/asset/model.py
mjxml/asset/texture.py
mjxml/body/__init__.py
mjxml/body/body.py
mjxml/body/camera.py
mjxml/body/geom.py
mjxml/body/inertial.py
mjxml/body/joint.py
mjxml/body/light.py
mjxml/body/site.py
mjxml/body/worldbody.py
mjxml/body/worldbodychildren.py
mjxml/contacts/__init__.py
mjxml/contacts/contacts.py
mjxml/contacts/exclude.py
mjxml/contacts/pair.py
mjxml/equality/__init__.py
mjxml/equality/connect.py
mjxml/equality/equality.py
mjxml/equality/jointeq.py
mjxml/equality/weld.py
mjxml-0.2.3.dist-info/METADATA
mjxml-0.2.3.dist-info/WHEEL
mjxml-0.2.3.dist-info/top_level.txt
mjxml-0.2.3.dist-info/RECORD
