Metadata-Version: 2.4
Name: mjxml
Version: 0.2.3
Summary: Utilities to programatically create MuJoCo XML configuration files
Author-email: Lena <lenazhu2007@gmail.com>
Requires-Python: >=3.13
Requires-Dist: numpy
Requires-Dist: pydantic
